{
  "endpoints": [
    "raokeo.com", "letamanh.net"
  ],
  "ips": [
  ],
  "measureUnits": [
    { "text": "kg" },
    { "text": "mét" },
    { "text": "lít" },
    { "text": "giờ" },
    { "text": "chai" },
    { "text": "bộ" },
    { "text": "bịch" },
    { "text": "bao" },
    { "text": "thùng" },
    { "text": "đôi" },
    { "text": "cái" }, 
    { "text": "trái" },
    { "text": "chậu" },
    { "text": "bó" },
    { "text": "cây" },
    { "text": "gói" },
    { "text": "viên" },
    { "text": "hộp" }
  ],
  "currencyUnits": [
    { "text": "Đồng", "meta": "vnd" },
    { "text": "Dollar", "meta": "usd" }
  ],
  "phoneTypes": [
    { "text": "Zalo" },
    { "text": "Whatsapp" },
    { "text": "Messenger" },
    { "text": "Viber" },
    { "text": "SMS" }
  ]
}
